tshift_llm/__init__.py
tshift_llm/tshift_llm.py
tshift_llm-0.1.3.dist-info/LICENSE
tshift_llm-0.1.3.dist-info/METADATA
tshift_llm-0.1.3.dist-info/WHEEL
tshift_llm-0.1.3.dist-info/top_level.txt
tshift_llm-0.1.3.dist-info/RECORD
