Metadata-Version: 2.1
Name: tshift-llm
Version: 0.1.3
Summary: A flexible LLM manager that shifts between multiple models
Author-email: Your Name <your.email@example.com>
License: # LICENSE
Project-URL: Homepage, https://github.com/yourusername/tshift-llm
Keywords: llm,ai,nlp,language model
Classifier: License :: OSI Approved :: MIT License
Classifier: Programming Language :: Python
Classifier: Programming Language :: Python :: 3
Requires-Python: >=3.7
License-File: LICENSE
Requires-Dist: litellm>=1.0.0
Requires-Dist: requests>=2.25.1
Provides-Extra: dev
Requires-Dist: pytest; extra == "dev"
